[
{
"time": "05:00",
"desc": "Itália x Países Baixos - Liga das Nações de Voleibol Feminino"
},
{
"time": "08:30",
"desc": "Brasil x Japão - Liga das Nações de Voleibol Feminino"
},
{
"time": "19:30",
"desc": "Operário x Ponte Preta - Brasileirão Série B"
},
{
"time": "19:30",
"desc": "Ceará SC x CRB - Brasileirão Série B"
},
{
"time": "19:30",
"desc": "Coritiba x Palmeiras - Brasileirão Série A"
},
{
"time": "20:30",
"desc": "Goiás x Sport Recife - Brasileirão Série B"
},
{
"time": "21:30",
"desc": "Náutico x Londrina - Brasileirão Série B"
},
{
"time": "21:30",
"desc": "São Paulo x Athletico-PR - Brasileirão Série A"
},
{
"time": "21:30",
"desc": "Internacional x Cruzeiro - Brasileirão Série A"
},
{
"time": "21:30",
"desc": "Chapecoense x Flamengo - Brasileirão Série A"
}
]





























































